scorecardpipeline/__init__.py
scorecardpipeline/auto_eda.py
scorecardpipeline/auto_report.py
scorecardpipeline/excel_writer.py
scorecardpipeline/feature_engineering.py
scorecardpipeline/feature_selection.py
scorecardpipeline/financial.py
scorecardpipeline/germancredit.csv
scorecardpipeline/logger.py
scorecardpipeline/matplot_chinese.ttf
scorecardpipeline/model.py
scorecardpipeline/processing.py
scorecardpipeline/rule.py
scorecardpipeline/rule_extraction.py
scorecardpipeline/scorecard.py
scorecardpipeline/template.xlsx
scorecardpipeline/utils.py
scorecardpipeline-0.1.38.7.dist-info/LICENSE
scorecardpipeline-0.1.38.7.dist-info/METADATA
scorecardpipeline-0.1.38.7.dist-info/WHEEL
scorecardpipeline-0.1.38.7.dist-info/top_level.txt
scorecardpipeline-0.1.38.7.dist-info/RECORD
