Metadata-Version: 2.1
Name: scorecardpipeline
Version: 0.1.38.7
Summary: 评分卡pipeline建模包，封装toad、scorecardpy、optbinning等评分卡建模相关组件，API风格与sklearn高度一致，自持自定义模型报告输出
Home-page: https://github.com/itlubber/scorecardpipeline
Author: itlubber
Author-email: itlubber@qq.com
License: MIT
Classifier: Operating System :: POSIX
Classifier: Operating System :: Microsoft :: Windows
Classifier: Operating System :: MacOS :: MacOS X
Classifier: Programming Language :: Python :: 3.6
Classifier: Programming Language :: Python :: 3.7
Classifier: Programming Language :: Python :: 3.8
Classifier: Programming Language :: Python :: 3.9
Classifier: Programming Language :: Python :: 3.10
Classifier: Programming Language :: Python :: 3.11
Classifier: Programming Language :: Python :: 3.12
Requires-Python: >=3.6
License-File: LICENSE
Requires-Dist: Cython
Requires-Dist: wget
Requires-Dist: numpy (<1.24.0,>1.23.1)
Requires-Dist: pandas
Requires-Dist: matplotlib
Requires-Dist: seaborn (>=0.10.0)
Requires-Dist: scipy (>=1.6.0)
Requires-Dist: statsmodels (<0.14,>=0.13.2)
Requires-Dist: scikit-learn (>=1.3.1)
Requires-Dist: toad
Requires-Dist: scorecardpy
Requires-Dist: ortools (<9.8.0,>=9.7.0)
Requires-Dist: ropwr (>=0.4.0)
Requires-Dist: optbinning
Requires-Dist: CairoSVG (>=2.7.0)
Requires-Dist: graphviz (>=0.20.1)
Requires-Dist: dtreeviz (>=2.2.1)
Requires-Dist: reportlab
Requires-Dist: svglib
Requires-Dist: category-encoders (>=2.6.0)
Requires-Dist: sklearn-pandas
Requires-Dist: sklearn2pmml
Requires-Dist: pypmml
Requires-Dist: joblib (>=0.12)
Requires-Dist: six (>=1.15.0)
Requires-Dist: openpyxl (>=3.0.10)
Requires-Dist: sweetviz
Requires-Dist: numexpr
Requires-Dist: cvxpy (>=1.4.1)
Requires-Dist: protobuf (>=5.27.0)
Requires-Dist: dill
